sqlite_to_postgres/__init__.py
sqlite_to_postgres/__main__.py
sqlite_to_postgres/main.py
sqlite_to_postgres-0.33.dist-info/DESCRIPTION.rst
sqlite_to_postgres-0.33.dist-info/METADATA
sqlite_to_postgres-0.33.dist-info/RECORD
sqlite_to_postgres-0.33.dist-info/WHEEL
sqlite_to_postgres-0.33.dist-info/metadata.json
sqlite_to_postgres-0.33.dist-info/top_level.txt
