Metadata-Version: 2.0
Name: sqlite-to-postgres
Version: 0.33
Summary: write sqlite file to postgres
Home-page: https://github.com/jeremiahsavage/sqlite_to_postgres
Author: Jeremiah H. Savage
Author-email: jeremiahsavage@gmail.com
License: Apache 2.0
Platform: UNKNOWN
Classifier: Development Status :: 3 - Alpha
Classifier: Intended Audience :: Developers
Classifier: License :: OSI Approved :: Apache Software License
Classifier: Programming Language :: Python
Classifier: Programming Language :: Python :: 2
Classifier: Programming Language :: Python :: 3
Requires-Dist: cdis-pipe-utils
Requires-Dist: sqlalchemy
